{
  "defaultTheme": ["light", "dark"],
  "color": {
    "red": "#FF3D3D",
    "orange": "#FF9E3D",
    "yellow": "#FFFF3D",
    "chartreuse": "#9FFF3D",
    "green": "#3EFF3D",
    "spring": "#3DFF9D",
    "cyan": "#3DFEFF",
    "sky": "#3D9DFF",
    "blue": "#3E3DFF",
    "purple": "#9F3DFF",
    "magenta": "#FF3DFF",
    "pink": "#FF3D9E",
    "white": "#DDDDDD",
    "black": "#333333"
  },
  "break": {
    "xs": {
      "type": "max-width",
      "value": "768px"
    },
    "sm": {
      "type": "min-width",
      "value": "768px"
    },
    "md": {
      "type": "min-width",
      "value": "992px"
    },
    "ls": {
      "type": "min-width",
      "value": "1200px"
    },
    "xl": {
      "type": "min-width",
      "value": "1920px"
    }
  },
  "themes": {
    "light": {
      "primary": "#42b983",
      "success": "#42b983",
      "warning": "#e7c000",
      "danger": "#cc0000",
      "bg": "#ffffff",
      "text": "#2c3e50",
      "bg-light": "#ffffff",
      "bg-middle": "#f6f6f6",
      "bg-dark": "#475050",
      "text-light": "#ffffff",
      "text-dark": "#2c3e50"
    },
    "dark": {
      "primary": "#42b983",
      "success": "#42b983",
      "warning": "#e7c000",
      "danger": "#cc0000",
      "bg": "#121212",
      "text": "#ffffff",
      "bg-light": "#ffffff",
      "bg-middle": "#f6f6f6",
      "bg-dark": "#475050",
      "text-light": "#ffffff",
      "text-dark": "#2c3e50"
    }
  }
}
